{
  "jbzl": {
    "gsmc": "深圳市海普瑞药业集团股份有限公司",
    "ywmc": "Shenzhen Hepalink Pharmaceutical Group Co.,Ltd.",
    "cym": "--",
    "agdm": "002399",
    "agjc": "海普瑞",
    "bgdm": "--",
    "bgjc": "--",
    "hgdm": "09989",
    "hgjc": "海普瑞",
    "zqlb": "深交所主板A股",
    "sshy": "医药制造",
    "ssjys": "深圳证券交易所",
    "sszjhhy": "制造业-医药制造业",
    "zjl": "单宇",
    "frdb": "李锂",
    "dm": "钱风奇",
    "dsz": "李锂",
    "zqswdb": "张文譞",
    "dlds": "易铭,吕川,黄鹏",
    "lxdh": "0755-26980200",
    "dzxx": "stock@hepalink.com",
    "cz": "0755-26980183",
    "gswz": "www.hepalink.com",
    "bgdz": "深圳市南山区松坪山郎山路21号",
    "zcdz": "深圳市南山区松坪山郎山路21号",
    "qy": "广东",
    "yzbm": "518057",
    "zczb": "14.67亿",
    "gsdj": "91440300279544901A",
    "gyrs": "1926",
    "glryrs": "13",
    "lssws": "北京中银(深圳)律师事务所,安理国际律师事务所",
    "kjssws": "安永华明会计师事务所(特殊普通合伙),安永会计师事务所",
    "gsjj": "    深圳市海普瑞药业集团股份有限公司于1998年成立于深圳,是拥有A+H双融资平台的领先跨国制药企业,主要业务覆盖肝素全产业链、生物大分子CDMO和创新药物的投资、开发及商业化。公司的三大板块业务相互协同,以临床未满足需求为驱动,致力于为全球患者提供高质量的安全有效药物和服务,护佑健康。",
    "jyfw": "一般经营项目是:开发、生产经营原料药(肝素钠、依诺肝素钠),从事货物及技术进出口(不含分销及国家专营、专控、专卖商品);非居住房地产租赁;住房租赁。(除依法须经批准的项目外,凭营业执照依法自主开展经营活动),许可经营项目是:物业管理。(依法须经批准的项目,经相关部门批准后方可开展经营活动,具体经营项目以相关部门批准文件或许可证件为准)"
  },
  "fxxg": {
    "clrq": "1998-04-21",
    "ssrq": "2010-05-06",
    "fxsyl": "73.27",
    "wsfxrq": "2010-04-26",
    "fxfs": "网下询价配售",
    "mgmz": "1.00",
    "fxl": "4010万",
    "mgfxj": "148.00",
    "fxfy": "2.180亿",
    "fxzsz": "59.35亿",
    "mjzjje": "57.17亿",
    "srkpj": "166.00",
    "srspj": "175.17",
    "srhsl": "70.02%",
    "srzgj": "188.00",
    "wxpszql": "1.10%",
    "djzql": "1.25%"
  },
  "Code": "SZ002399",
  "CodeType": "ABStock",
  "SecuCode": "002399.SZ",
  "SecurityCode": "002399",
  "SecurityShortName": "海普瑞",
  "MarketCode": "02",
  "Market": "SZ",
  "SecurityType": null,
  "ExpireTime": "/Date(-62135596800000)/"
}