{
  "jbzl": {
    "gsmc": "紫光股份有限公司",
    "ywmc": "Unisplendour Corporation Limited",
    "cym": "清华紫光->G紫光",
    "agdm": "000938",
    "agjc": "紫光股份",
    "bgdm": "--",
    "bgjc": "--",
    "hgdm": "H5088",
    "hgjc": "紫光股份",
    "zqlb": "深交所主板A股",
    "sshy": "电子信息",
    "ssjys": "深圳证券交易所",
    "sszjhhy": "制造业-计算机、通信和其他电子设备制造业",
    "zjl": "王竑弢",
    "frdb": "于英涛",
    "dm": "张蔚",
    "dsz": "于英涛",
    "zqswdb": "刁月霞",
    "dlds": "周绍朋,徐猛,徐经长,万红",
    "lxdh": "010-62770008",
    "dzxx": "thunis@thunis.com",
    "cz": "010-62770880",
    "gswz": "www.thunis.com",
    "bgdz": "北京市海淀区清华大学紫光大楼",
    "zcdz": "北京市海淀区清华大学紫光大楼",
    "qy": "北京",
    "yzbm": "100084",
    "zczb": "28.60亿",
    "gsdj": "91110000700218641X",
    "gyrs": "17242",
    "glryrs": "10",
    "lssws": "北京市重光律师事务所",
    "kjssws": "安永华明会计师事务所(特殊普通合伙)",
    "gsjj": "    紫光股份有限公司是主营信息电子产业的中国高科技A股上市公司(股票简称紫光股份,代码000938),成立于1999年3月。紫光股份有限公司结合全球信息产业的发展趋势及自身优势业务的特点,将公司战略聚焦于IT服务领域,向云计算、移动互联网和大数据处理等信息技术的行业应用领域全面深入,并成为集现代信息系统研发、建设、运营、维护于一体的全产业链服务提供商。目前,紫光股份的核心业务基本覆盖IT服务的重要领域:硬件方面提供智能网络设备、存储系统、全系列服务器等为主的面向未来计算架构的先进装备。软件方面提供从桌面端到移动端的各重点行业的应用软件解决方案。技术服务方面涵盖技术咨询、基础设施解决方案和支持服务。软硬件产品和服务都在紫光股份领先的顶层设计中得到有效整合,使信息化系统展现出最优化、完整一体的运行效果。紫光股份有能力为大型客户的信息化需求提供完整、领先的IT服务。未来,紫光股份将重点拓展云服务的全球业务,在提供现有云计算基础设施建设服务、云计算行业应用解决方案服务等两个基础层级服务之上,向云计算的平台化服务加速迈进,成为国际化的大型云服务集团企业,并最终将紫光股份成功塑造为中国乃至世界最全面和领先的新IT服务平台型企业之一。新的历史时期,紫光股份希望在“中国梦”的感召下,持续创新、跨越成长,与客户、合作伙伴、股东、员工一起,携手同行,共创辉煌!",
    "jyfw": "一般项目:技术服务、技术开发、技术咨询、技术交流、技术转让、技术推广;计算机软硬件及辅助设备零售;计算机软硬件及辅助设备批发;计算机软硬件及外围设备制造;电子产品销售;电子元器件零售;电子元器件批发;通信设备销售;通信设备制造;广播影视设备销售;玩具销售;仪器仪表销售;文具用品零售;文具用品批发;办公设备销售;办公用品销售;文化、办公用设备制造;计算机系统服务;计算机及办公设备维修;数据处理服务;软件开发;软件销售;软件外包服务;企业管理;以自有资金从事投资活动;非居住房地产租赁;物业管理;专业设计服务;会议及展览服务;货物进出口;进出口代理。(除依法须经批准的项目外,凭营业执照依法自主开展经营活动)"
  },
  "fxxg": {
    "clrq": "1999-03-18",
    "ssrq": "1999-11-04",
    "fxsyl": "27.98",
    "wsfxrq": "1999-08-25",
    "fxfs": "网下定价发行",
    "mgmz": "1.00",
    "fxl": "4000万",
    "mgfxj": "11.75",
    "fxfy": "1087万",
    "fxzsz": "4.700亿",
    "mjzjje": "4.574亿",
    "srkpj": "26.75",
    "srspj": "51.92",
    "srhsl": "73.74%",
    "srzgj": "55.99",
    "wxpszql": "--",
    "djzql": "0.37%"
  },
  "Code": "SZ000938",
  "CodeType": "ABStock",
  "SecuCode": "000938.SZ",
  "SecurityCode": "000938",
  "SecurityShortName": "紫光股份",
  "MarketCode": "02",
  "Market": "SZ",
  "SecurityType": null,
  "ExpireTime": "/Date(-62135596800000)/"
}